{
    "_links":  {
                   "self":  {
                                "href":  "https://eu.api.blizzard.com/data/wow/profession/171/skill-tier/2906?namespace=static-12.0.1_65617-eu"
                            }
               },
    "id":  2906,
    "name":  "Midnight Alchemy",
    "minimum_skill_level":  1,
    "maximum_skill_level":  100,
    "categories":  [
                       {
                           "name":  "Recrafting",
                           "recipes":  [
                                           {
                                               "key":  {
                                                           "href":  "https://eu.api.blizzard.com/data/wow/recipe/51519?namespace=static-12.0.1_65617-eu"
                                                       },
                                               "name":  "Recraft Equipment",
                                               "id":  51519
                                           },
                                           {
                                               "key":  {
                                                           "href":  "https://eu.api.blizzard.com/data/wow/recipe/52781?namespace=static-12.0.1_65617-eu"
                                                       },
                                               "name":  "Recycle Potions",
                                               "id":  52781
                                           },
                                           {
                                               "key":  {
                                                           "href":  "https://eu.api.blizzard.com/data/wow/recipe/52782?namespace=static-12.0.1_65617-eu"
                                                       },
                                               "name":  "Recycle Flasks",
                                               "id":  52782
                                           }
                                       ]
                       },
                       {
                           "name":  "Void Potions",
                           "recipes":  [
                                           {
                                               "key":  {
                                                           "href":  "https://eu.api.blizzard.com/data/wow/recipe/52681?namespace=static-12.0.1_65617-eu"
                                                       },
                                               "name":  "Entropic Extract",
                                               "id":  52681
                                           },
                                           {
                                               "key":  {
                                                           "href":  "https://eu.api.blizzard.com/data/wow/recipe/52686?namespace=static-12.0.1_65617-eu"
                                                       },
                                               "name":  "Potion of Recklessness",
                                               "id":  52686
                                           },
                                           {
                                               "key":  {
                                                           "href":  "https://eu.api.blizzard.com/data/wow/recipe/52687?namespace=static-12.0.1_65617-eu"
                                                       },
                                               "name":  "Draught of Rampant Abandon",
                                               "id":  52687
                                           },
                                           {
                                               "key":  {
                                                           "href":  "https://eu.api.blizzard.com/data/wow/recipe/52689?namespace=static-12.0.1_65617-eu"
                                                       },
                                               "name":  "Potion of Devoured Dreams",
                                               "id":  52689
                                           },
                                           {
                                               "key":  {
                                                           "href":  "https://eu.api.blizzard.com/data/wow/recipe/52691?namespace=static-12.0.1_65617-eu"
                                                       },
                                               "name":  "Amani Extract",
                                               "id":  52691
                                           },
                                           {
                                               "key":  {
                                                           "href":  "https://eu.api.blizzard.com/data/wow/recipe/52694?namespace=static-12.0.1_65617-eu"
                                                       },
                                               "name":  "Void-Shrouded Tincture",
                                               "id":  52694
                                           }
                                       ]
                       },
                       {
                           "name":  "Transmutations",
                           "recipes":  [
                                           {
                                               "key":  {
                                                           "href":  "https://eu.api.blizzard.com/data/wow/recipe/52682?namespace=static-12.0.1_65617-eu"
                                                       },
                                               "name":  "Composite Flora",
                                               "id":  52682
                                           },
                                           {
                                               "key":  {
                                                           "href":  "https://eu.api.blizzard.com/data/wow/recipe/52683?namespace=static-12.0.1_65617-eu"
                                                       },
                                               "name":  "Wondrous Synergist",
                                               "id":  52683
                                           },
                                           {
                                               "key":  {
                                                           "href":  "https://eu.api.blizzard.com/data/wow/recipe/52714?namespace=static-12.0.1_65617-eu"
                                                       },
                                               "name":  "Transmute: Mote of Wild Magic",
                                               "id":  52714
                                           },
                                           {
                                               "key":  {
                                                           "href":  "https://eu.api.blizzard.com/data/wow/recipe/52715?namespace=static-12.0.1_65617-eu"
                                                       },
                                               "name":  "Transmute: Mote of Pure Void",
                                               "id":  52715
                                           },
                                           {
                                               "key":  {
                                                           "href":  "https://eu.api.blizzard.com/data/wow/recipe/52716?namespace=static-12.0.1_65617-eu"
                                                       },
                                               "name":  "Transmute: Mote of Primal Energy",
                                               "id":  52716
                                           },
                                           {
                                               "key":  {
                                                           "href":  "https://eu.api.blizzard.com/data/wow/recipe/52717?namespace=static-12.0.1_65617-eu"
                                                       },
                                               "name":  "Transmute: Mote of Light",
                                               "id":  52717
                                           },
                                           {
                                               "key":  {
                                                           "href":  "https://eu.api.blizzard.com/data/wow/recipe/52718?namespace=static-12.0.1_65617-eu"
                                                       },
                                               "name":  "Box of Rocks",
                                               "id":  52718
                                           },
                                           {
                                               "key":  {
                                                           "href":  "https://eu.api.blizzard.com/data/wow/recipe/52719?namespace=static-12.0.1_65617-eu"
                                                       },
                                               "name":  "Bouquet of Herbs",
                                               "id":  52719
                                           },
                                           {
                                               "key":  {
                                                           "href":  "https://eu.api.blizzard.com/data/wow/recipe/52720?namespace=static-12.0.1_65617-eu"
                                                       },
                                               "name":  "School of Gems",
                                               "id":  52720
                                           }
                                       ]
                       },
                       {
                           "name":  "Cauldrons",
                           "recipes":  [
                                           {
                                               "key":  {
                                                           "href":  "https://eu.api.blizzard.com/data/wow/recipe/52684?namespace=static-12.0.1_65617-eu"
                                                       },
                                               "name":  "Voidlight Potion Cauldron",
                                               "id":  52684
                                           },
                                           {
                                               "key":  {
                                                           "href":  "https://eu.api.blizzard.com/data/wow/recipe/52701?namespace=static-12.0.1_65617-eu"
                                                       },
                                               "name":  "Cauldron of Sin\u0027dorei Flasks",
                                               "id":  52701
                                           }
                                       ]
                       },
                       {
                           "name":  "Light Potions",
                           "recipes":  [
                                           {
                                               "key":  {
                                                           "href":  "https://eu.api.blizzard.com/data/wow/recipe/52685?namespace=static-12.0.1_65617-eu"
                                                       },
                                               "name":  "Light\u0027s Preservation",
                                               "id":  52685
                                           },
                                           {
                                               "key":  {
                                                           "href":  "https://eu.api.blizzard.com/data/wow/recipe/52690?namespace=static-12.0.1_65617-eu"
                                                       },
                                               "name":  "Potion of Zealotry",
                                               "id":  52690
                                           },
                                           {
                                               "key":  {
                                                           "href":  "https://eu.api.blizzard.com/data/wow/recipe/52692?namespace=static-12.0.1_65617-eu"
                                                       },
                                               "name":  "Lightfused Mana Potion",
                                               "id":  52692
                                           },
                                           {
                                               "key":  {
                                                           "href":  "https://eu.api.blizzard.com/data/wow/recipe/52693?namespace=static-12.0.1_65617-eu"
                                                       },
                                               "name":  "Silvermoon Health Potion",
                                               "id":  52693
                                           },
                                           {
                                               "key":  {
                                                           "href":  "https://eu.api.blizzard.com/data/wow/recipe/52695?namespace=static-12.0.1_65617-eu"
                                                       },
                                               "name":  "Refreshing Serum",
                                               "id":  52695
                                           },
                                           {
                                               "key":  {
                                                           "href":  "https://eu.api.blizzard.com/data/wow/recipe/52696?namespace=static-12.0.1_65617-eu"
                                                       },
                                               "name":  "Light\u0027s Potential",
                                               "id":  52696
                                           },
                                           {
                                               "key":  {
                                                           "href":  "https://eu.api.blizzard.com/data/wow/recipe/52713?namespace=static-12.0.1_65617-eu"
                                                       },
                                               "name":  "Enlightenment Tonic",
                                               "id":  52713
                                           }
                                       ]
                       },
                       {
                           "name":  "Alchemist Stones",
                           "recipes":  [
                                           {
                                               "key":  {
                                                           "href":  "https://eu.api.blizzard.com/data/wow/recipe/52688?namespace=static-12.0.1_65617-eu"
                                                       },
                                               "name":  "Primal Philosopher\u0027s Stone",
                                               "id":  52688
                                           },
                                           {
                                               "key":  {
                                                           "href":  "https://eu.api.blizzard.com/data/wow/recipe/52712?namespace=static-12.0.1_65617-eu"
                                                       },
                                               "name":  "Magister\u0027s Alchemist Stone",
                                               "id":  52712
                                           }
                                       ]
                       },
                       {
                           "name":  "Haranir Phials",
                           "recipes":  [
                                           {
                                               "key":  {
                                                           "href":  "https://eu.api.blizzard.com/data/wow/recipe/52697?namespace=static-12.0.1_65617-eu"
                                                       },
                                               "name":  "Haranir Phial of Finesse",
                                               "id":  52697
                                           },
                                           {
                                               "key":  {
                                                           "href":  "https://eu.api.blizzard.com/data/wow/recipe/52699?namespace=static-12.0.1_65617-eu"
                                                       },
                                               "name":  "Haranir Phial of Ingenuity",
                                               "id":  52699
                                           },
                                           {
                                               "key":  {
                                                           "href":  "https://eu.api.blizzard.com/data/wow/recipe/52700?namespace=static-12.0.1_65617-eu"
                                                       },
                                               "name":  "Haranir Phial of Perception",
                                               "id":  52700
                                           }
                                       ]
                       },
                       {
                           "name":  "Sin\u0027dorei Flasks",
                           "recipes":  [
                                           {
                                               "key":  {
                                                           "href":  "https://eu.api.blizzard.com/data/wow/recipe/52702?namespace=static-12.0.1_65617-eu"
                                                       },
                                               "name":  "Flask of Thalassian Resistance",
                                               "id":  52702
                                           },
                                           {
                                               "key":  {
                                                           "href":  "https://eu.api.blizzard.com/data/wow/recipe/52703?namespace=static-12.0.1_65617-eu"
                                                       },
                                               "name":  "Flask of the Magisters",
                                               "id":  52703
                                           },
                                           {
                                               "key":  {
                                                           "href":  "https://eu.api.blizzard.com/data/wow/recipe/52704?namespace=static-12.0.1_65617-eu"
                                                       },
                                               "name":  "Flask of the Blood Knights",
                                               "id":  52704
                                           },
                                           {
                                               "key":  {
                                                           "href":  "https://eu.api.blizzard.com/data/wow/recipe/52705?namespace=static-12.0.1_65617-eu"
                                                       },
                                               "name":  "Flask of the Shattered Sun",
                                               "id":  52705
                                           }
                                       ]
                       },
                       {
                           "name":  "Vicious Flasks",
                           "recipes":  [
                                           {
                                               "key":  {
                                                           "href":  "https://eu.api.blizzard.com/data/wow/recipe/52710?namespace=static-12.0.1_65617-eu"
                                                       },
                                               "name":  "Vicious Thalassian Flask of Honor",
                                               "id":  52710
                                           }
                                       ]
                       },
                       {
                           "name":  "House Decor",
                           "recipes":  [
                                           {
                                               "key":  {
                                                           "href":  "https://eu.api.blizzard.com/data/wow/recipe/52784?namespace=static-12.0.1_65617-eu"
                                                       },
                                               "name":  "Entropic Illuminant",
                                               "id":  52784
                                           },
                                           {
                                               "key":  {
                                                           "href":  "https://eu.api.blizzard.com/data/wow/recipe/52785?namespace=static-12.0.1_65617-eu"
                                                       },
                                               "name":  "Rootbound Vat",
                                               "id":  52785
                                           },
                                           {
                                               "key":  {
                                                           "href":  "https://eu.api.blizzard.com/data/wow/recipe/52786?namespace=static-12.0.1_65617-eu"
                                                       },
                                               "name":  "Sunsmoke Censer",
                                               "id":  52786
                                           },
                                           {
                                               "key":  {
                                                           "href":  "https://eu.api.blizzard.com/data/wow/recipe/52787?namespace=static-12.0.1_65617-eu"
                                                       },
                                               "name":  "Riftstone",
                                               "id":  52787
                                           },
                                           {
                                               "key":  {
                                                           "href":  "https://eu.api.blizzard.com/data/wow/recipe/52788?namespace=static-12.0.1_65617-eu"
                                                       },
                                               "name":  "Haranir Preserving Agents",
                                               "id":  52788
                                           },
                                           {
                                               "key":  {
                                                           "href":  "https://eu.api.blizzard.com/data/wow/recipe/52789?namespace=static-12.0.1_65617-eu"
                                                       },
                                               "name":  "Silvermoon Spire Fountain",
                                               "id":  52789
                                           }
                                       ]
                       },
                       {
                           "name":  "Appendix I - Terms",
                           "recipes":  [
                                           {
                                               "key":  {
                                                           "href":  "https://eu.api.blizzard.com/data/wow/recipe/56596?namespace=static-12.0.1_65617-eu"
                                                       },
                                               "name":  "Quality",
                                               "id":  56596
                                           },
                                           {
                                               "key":  {
                                                           "href":  "https://eu.api.blizzard.com/data/wow/recipe/56597?namespace=static-12.0.1_65617-eu"
                                                       },
                                               "name":  "Sparks",
                                               "id":  56597
                                           },
                                           {
                                               "key":  {
                                                           "href":  "https://eu.api.blizzard.com/data/wow/recipe/56598?namespace=static-12.0.1_65617-eu"
                                                       },
                                               "name":  "Artisan Alchemist\u0027s Moxie",
                                               "id":  56598
                                           },
                                           {
                                               "key":  {
                                                           "href":  "https://eu.api.blizzard.com/data/wow/recipe/56599?namespace=static-12.0.1_65617-eu"
                                                       },
                                               "name":  "Concentration",
                                               "id":  56599
                                           },
                                           {
                                               "key":  {
                                                           "href":  "https://eu.api.blizzard.com/data/wow/recipe/56600?namespace=static-12.0.1_65617-eu"
                                                       },
                                               "name":  "Knowledge",
                                               "id":  56600
                                           }
                                       ]
                       },
                       {
                           "name":  "Appendix II - Stats",
                           "recipes":  [
                                           {
                                               "key":  {
                                                           "href":  "https://eu.api.blizzard.com/data/wow/recipe/56601?namespace=static-12.0.1_65617-eu"
                                                       },
                                               "name":  "Skill",
                                               "id":  56601
                                           },
                                           {
                                               "key":  {
                                                           "href":  "https://eu.api.blizzard.com/data/wow/recipe/56602?namespace=static-12.0.1_65617-eu"
                                                       },
                                               "name":  "Multicraft",
                                               "id":  56602
                                           },
                                           {
                                               "key":  {
                                                           "href":  "https://eu.api.blizzard.com/data/wow/recipe/56603?namespace=static-12.0.1_65617-eu"
                                                       },
                                               "name":  "Resourcefulness",
                                               "id":  56603
                                           },
                                           {
                                               "key":  {
                                                           "href":  "https://eu.api.blizzard.com/data/wow/recipe/56604?namespace=static-12.0.1_65617-eu"
                                                       },
                                               "name":  "Ingenuity",
                                               "id":  56604
                                           }
                                       ]
                       }
                   ]
}
